<annotation>
	<folder/>
	<filename>N_3060.jpg</filename>
	<path>MAFA-Crop-Yolo/train//N_3060.jpg</path>
	<source>
		<database>Unknown</database>
	</source>
	<size>
		<width>526</width>
		<height>356</height>
		<depth>3</depth>
	</size>
	<segmented>0</segmented>
	<object>
		<name>NoMask</name>
		<pose>Unspecified</pose>
		<truncated>0</truncated>
		<difficult>0</difficult>
		<bndbox>
			<xmin>263</xmin>
			<ymin>128</ymin>
			<xmax>308</xmax>
			<ymax>173</ymax>
		</bndbox>
	</object>
</annotation>
